README.md
setup.py
globomap_auth_manager/__init__.py
globomap_auth_manager/auth.py
globomap_auth_manager/exceptions.py
globomap_auth_manager/keystone_auth.py
globomap_auth_manager/redis_client.py
globomap_auth_manager/settings.py
globomap_auth_manager.egg-info/PKG-INFO
globomap_auth_manager.egg-info/SOURCES.txt
globomap_auth_manager.egg-info/dependency_links.txt
globomap_auth_manager.egg-info/requires.txt
globomap_auth_manager.egg-info/top_level.txt