Metadata-Version: 1.0
Name: globomap-auth-manager
Version: 0.0.16
Summary: Library to manage authorization for GloboMAP
Home-page: https://github.com/globocom/globomap-auth-manager
Author: Ederson Brilhante
Author-email: ederson.brilhante@corp.globo.com
License: UNKNOWN
Platform: UNKNOWN
